Metadata-Version: 2.1
Name: sneaky-reader
Version: 0.1.2
Summary: undercover book-reader in your terminal
Home-page: https://github.com/gusye1234/sneaky-reader
Author: JianbaiYe
Classifier: Programming Language :: Python :: 3
Classifier: License :: OSI Approved :: MIT License
Classifier: Operating System :: OS Independent
Requires-Python: >=3.6
